{
  "Contributor ID": "db5fac30-88e5-4585-1169-08dc623ec532",
  "Do you consider U.S. English to be your first language": "No Response Supplied",
  "What language(s) do you speak": "No Response Supplied",
  "What age did you start speaking English": "No Response Supplied",
  "I consent to have my voice samples shared in public at research conferences and similar professional meetings, and to have digital audio files of my voice be shared as part of professional research publications.": "Yes",
  "Etiology": "ALS",
  "BlockNumber": 4,
  "Files": [
    {
      "Filename": "db5fac30-88e5-4585-1169-08dc623ec532_1129_5723_16kHz.wav",
      "Created": "2024-07-01 18:59:54",
      "CreatedOrModified": "2025-04-11 11:12:28",
      "Comment": "",
      "Prompt": {
        "Prompt Text": "You can imagine how surprised and puzzled she was.",
        "Transcript": "You can imagine how surprised and puzzled she was.",
        "Category Description": "Novel Sentences",
        "Sub Category Description": "",
        "Translation": "Sie können sich vorstellen, wie überrascht und verwirrt sie war."
      },
      "Ratings": [
        {
          "Level": "1",
          "Comment": "",
          "Other": "",
          "Dimension Description": "Audible inspiration",
          "Dimension Category Description": "ALS",
          "RatingDate": "2025-06-07 13:22:31"
        },
        {
          "Level": "1",
          "Comment": "",
          "Other": "",
          "Dimension Description": "Excess and equal stress",
          "Dimension Category Description": "ALS",
          "RatingDate": "2025-06-07 13:22:31"
        },
        {
          "Level": "1",
          "Comment": "",
          "Other": "",
          "Dimension Description": "Inappropriate silences",
          "Dimension Category Description": "ALS",
          "RatingDate": "2025-06-07 13:22:31"
        },
        {
          "Level": "1",
          "Comment": "",
          "Other": "",
          "Dimension Description": "Nasal emission ",
          "Dimension Category Description": "ALS",
          "RatingDate": "2025-06-07 13:22:31"
        },
        {
          "Level": "1",
          "Comment": "",
          "Other": "",
          "Dimension Description": "Prolonged intervals",
          "Dimension Category Description": "ALS",
          "RatingDate": "2025-06-07 13:22:31"
        },
        {
          "Level": "1",
          "Comment": "",
          "Other": "",
          "Dimension Description": "Prolonged phonemes",
          "Dimension Category Description": "ALS",
          "RatingDate": "2025-06-07 13:22:31"
        },
        {
          "Level": "1",
          "Comment": "",
          "Other": "",
          "Dimension Description": "Strained-strangled voice",
          "Dimension Category Description": "ALS",
          "RatingDate": "2025-06-07 13:22:31"
        },
        {
          "Level": "2",
          "Comment": "",
          "Other": "",
          "Dimension Description": "Reduced stress",
          "Dimension Category Description": "ALS",
          "RatingDate": "2025-06-07 13:22:31"
        },
        {
          "Level": "2",
          "Comment": "",
          "Other": "",
          "Dimension Description": "Short phrases",
          "Dimension Category Description": "ALS",
          "RatingDate": "2025-06-07 13:22:31"
        },
        {
          "Level": "2",
          "Comment": "",
          "Other": "",
          "Dimension Description": "Slow rate",
          "Dimension Category Description": "ALS",
          "RatingDate": "2025-06-07 13:22:31"
        },
        {
          "Level": "3",
          "Comment": "",
          "Other": "",
          "Dimension Description": "Breathiness",
          "Dimension Category Description": "ALS",
          "RatingDate": "2025-06-07 13:22:31"
        },
        {
          "Level": "3",
          "Comment": "",
          "Other": "",
          "Dimension Description": "Harsh voice ",
          "Dimension Category Description": "ALS",
          "RatingDate": "2025-06-07 13:22:31"
        },
        {
          "Level": "3",
          "Comment": "",
          "Other": "",
          "Dimension Description": "Low pitch",
          "Dimension Category Description": "ALS",
          "RatingDate": "2025-06-07 13:22:31"
        },
        {
          "Level": "4",
          "Comment": "",
          "Other": "",
          "Dimension Description": "Hypernasality",
          "Dimension Category Description": "ALS",
          "RatingDate": "2025-06-07 13:22:31"
        },
        {
          "Level": "4",
          "Comment": "",
          "Other": "",
          "Dimension Description": "Monoloudness",
          "Dimension Category Description": "ALS",
          "RatingDate": "2025-06-07 13:22:31"
        },
        {
          "Level": "4",
          "Comment": "",
          "Other": "",
          "Dimension Description": "Monopitch",
          "Dimension Category Description": "ALS",
          "RatingDate": "2025-06-07 13:22:31"
        },
        {
          "Level": "5",
          "Comment": "",
          "Other": "",
          "Dimension Description": "Distorted vowels",
          "Dimension Category Description": "ALS",
          "RatingDate": "2025-06-07 13:22:31"
        },
        {
          "Level": "5",
          "Comment": "",
          "Other": "",
          "Dimension Description": "Intelligibility",
          "Dimension Category Description": "ALS",
          "RatingDate": "2025-06-07 13:22:31"
        },
        {
          "Level": "6",
          "Comment": "",
          "Other": "",
          "Dimension Description": "Imprecise consonants",
          "Dimension Category Description": "ALS",
          "RatingDate": "2025-06-07 13:22:31"
        },
        {
          "Level": "6",
          "Comment": "",
          "Other": "",
          "Dimension Description": "Naturalness",
          "Dimension Category Description": "ALS",
          "RatingDate": "2025-06-07 13:22:31"
        }
      ]
    },
    {
      "Filename": "db5fac30-88e5-4585-1169-08dc623ec532_2215_5723_16kHz.wav",
      "Created": "2024-07-01 19:00:16",
      "CreatedOrModified": "2025-04-11 11:18:56",
      "Comment": "",
      "Prompt": {
        "Prompt Text": "When I was a young boy, father always said I was a born business manager.",
        "Transcript": "When I was a young boy, father always said I was a born business manager.",
        "Category Description": "Novel Sentences",
        "Sub Category Description": "",
        "Translation": "Als ich ein junger Junge war, sagte Vater immer, ich sei ein geborener Geschäftsleiter."
      },
      "Ratings": [
        {
          "Level": "1",
          "Comment": "",
          "Other": "",
          "Dimension Description": "Audible inspiration",
          "Dimension Category Description": "ALS",
          "RatingDate": "2025-06-07 13:23:13"
        },
        {
          "Level": "1",
          "Comment": "",
          "Other": "",
          "Dimension Description": "Excess and equal stress",
          "Dimension Category Description": "ALS",
          "RatingDate": "2025-06-07 13:23:13"
        },
        {
          "Level": "1",
          "Comment": "",
          "Other": "",
          "Dimension Description": "Inappropriate silences",
          "Dimension Category Description": "ALS",
          "RatingDate": "2025-06-07 13:23:13"
        },
        {
          "Level": "1",
          "Comment": "",
          "Other": "",
          "Dimension Description": "Nasal emission ",
          "Dimension Category Description": "ALS",
          "RatingDate": "2025-06-07 13:23:13"
        },
        {
          "Level": "1",
          "Comment": "",
          "Other": "",
          "Dimension Description": "Prolonged intervals",
          "Dimension Category Description": "ALS",
          "RatingDate": "2025-06-07 13:23:13"
        },
        {
          "Level": "1",
          "Comment": "",
          "Other": "",
          "Dimension Description": "Prolonged phonemes",
          "Dimension Category Description": "ALS",
          "RatingDate": "2025-06-07 13:23:13"
        },
        {
          "Level": "2",
          "Comment": "",
          "Other": "",
          "Dimension Description": "Harsh voice ",
          "Dimension Category Description": "ALS",
          "RatingDate": "2025-06-07 13:23:13"
        },
        {
          "Level": "2",
          "Comment": "",
          "Other": "",
          "Dimension Description": "Short phrases",
          "Dimension Category Description": "ALS",
          "RatingDate": "2025-06-07 13:23:13"
        },
        {
          "Level": "2",
          "Comment": "",
          "Other": "",
          "Dimension Description": "Strained-strangled voice",
          "Dimension Category Description": "ALS",
          "RatingDate": "2025-06-07 13:23:13"
        },
        {
          "Level": "3",
          "Comment": "",
          "Other": "",
          "Dimension Description": "Breathiness",
          "Dimension Category Description": "ALS",
          "RatingDate": "2025-06-07 13:23:13"
        },
        {
          "Level": "3",
          "Comment": "",
          "Other": "",
          "Dimension Description": "Low pitch",
          "Dimension Category Description": "ALS",
          "RatingDate": "2025-06-07 13:23:13"
        },
        {
          "Level": "3",
          "Comment": "",
          "Other": "",
          "Dimension Description": "Reduced stress",
          "Dimension Category Description": "ALS",
          "RatingDate": "2025-06-07 13:23:13"
        },
        {
          "Level": "3",
          "Comment": "",
          "Other": "",
          "Dimension Description": "Slow rate",
          "Dimension Category Description": "ALS",
          "RatingDate": "2025-06-07 13:23:13"
        },
        {
          "Level": "4",
          "Comment": "",
          "Other": "",
          "Dimension Description": "Hypernasality",
          "Dimension Category Description": "ALS",
          "RatingDate": "2025-06-07 13:23:13"
        },
        {
          "Level": "4",
          "Comment": "",
          "Other": "",
          "Dimension Description": "Monoloudness",
          "Dimension Category Description": "ALS",
          "RatingDate": "2025-06-07 13:23:13"
        },
        {
          "Level": "4",
          "Comment": "",
          "Other": "",
          "Dimension Description": "Monopitch",
          "Dimension Category Description": "ALS",
          "RatingDate": "2025-06-07 13:23:13"
        },
        {
          "Level": "5",
          "Comment": "",
          "Other": "",
          "Dimension Description": "Distorted vowels",
          "Dimension Category Description": "ALS",
          "RatingDate": "2025-06-07 13:23:13"
        },
        {
          "Level": "5",
          "Comment": "",
          "Other": "",
          "Dimension Description": "Imprecise consonants",
          "Dimension Category Description": "ALS",
          "RatingDate": "2025-06-07 13:23:13"
        },
        {
          "Level": "5",
          "Comment": "",
          "Other": "",
          "Dimension Description": "Intelligibility",
          "Dimension Category Description": "ALS",
          "RatingDate": "2025-06-07 13:23:13"
        },
        {
          "Level": "6",
          "Comment": "",
          "Other": "",
          "Dimension Description": "Naturalness",
          "Dimension Category Description": "ALS",
          "RatingDate": "2025-06-07 13:23:13"
        }
      ]
    },
    {
      "Filename": "db5fac30-88e5-4585-1169-08dc623ec532_8876_5723_16kHz.wav",
      "Created": "2024-07-01 19:00:40",
      "CreatedOrModified": "2025-04-11 11:12:42",
      "Comment": "",
      "Prompt": {
        "Prompt Text": "Now is our one moment of glory.",
        "Transcript": "Now is our one moment of glory.",
        "Category Description": "Novel Sentences",
        "Sub Category Description": "",
        "Translation": "Jetzt ist unser einziger Moment der Herrlichkeit."
      },
      "Ratings": [
        {
          "Level": "1",
          "Comment": "",
          "Other": "",
          "Dimension Description": "Audible inspiration",
          "Dimension Category Description": "ALS",
          "RatingDate": "2025-06-07 13:23:51"
        },
        {
          "Level": "1",
          "Comment": "",
          "Other": "",
          "Dimension Description": "Excess and equal stress",
          "Dimension Category Description": "ALS",
          "RatingDate": "2025-06-07 13:23:51"
        },
        {
          "Level": "1",
          "Comment": "",
          "Other": "",
          "Dimension Description": "Inappropriate silences",
          "Dimension Category Description": "ALS",
          "RatingDate": "2025-06-07 13:23:51"
        },
        {
          "Level": "1",
          "Comment": "",
          "Other": "",
          "Dimension Description": "Nasal emission ",
          "Dimension Category Description": "ALS",
          "RatingDate": "2025-06-07 13:23:51"
        },
        {
          "Level": "1",
          "Comment": "",
          "Other": "",
          "Dimension Description": "Prolonged intervals",
          "Dimension Category Description": "ALS",
          "RatingDate": "2025-06-07 13:23:51"
        },
        {
          "Level": "1",
          "Comment": "",
          "Other": "",
          "Dimension Description": "Prolonged phonemes",
          "Dimension Category Description": "ALS",
          "RatingDate": "2025-06-07 13:23:51"
        },
        {
          "Level": "1",
          "Comment": "",
          "Other": "",
          "Dimension Description": "Short phrases",
          "Dimension Category Description": "ALS",
          "RatingDate": "2025-06-07 13:23:51"
        },
        {
          "Level": "2",
          "Comment": "",
          "Other": "",
          "Dimension Description": "Harsh voice ",
          "Dimension Category Description": "ALS",
          "RatingDate": "2025-06-07 13:23:51"
        },
        {
          "Level": "2",
          "Comment": "",
          "Other": "",
          "Dimension Description": "Low pitch",
          "Dimension Category Description": "ALS",
          "RatingDate": "2025-06-07 13:23:51"
        },
        {
          "Level": "2",
          "Comment": "",
          "Other": "",
          "Dimension Description": "Reduced stress",
          "Dimension Category Description": "ALS",
          "RatingDate": "2025-06-07 13:23:51"
        },
        {
          "Level": "2",
          "Comment": "",
          "Other": "",
          "Dimension Description": "Slow rate",
          "Dimension Category Description": "ALS",
          "RatingDate": "2025-06-07 13:23:51"
        },
        {
          "Level": "2",
          "Comment": "",
          "Other": "",
          "Dimension Description": "Strained-strangled voice",
          "Dimension Category Description": "ALS",
          "RatingDate": "2025-06-07 13:23:51"
        },
        {
          "Level": "3",
          "Comment": "",
          "Other": "",
          "Dimension Description": "Breathiness",
          "Dimension Category Description": "ALS",
          "RatingDate": "2025-06-07 13:23:51"
        },
        {
          "Level": "3",
          "Comment": "",
          "Other": "",
          "Dimension Description": "Hypernasality",
          "Dimension Category Description": "ALS",
          "RatingDate": "2025-06-07 13:23:51"
        },
        {
          "Level": "3",
          "Comment": "",
          "Other": "",
          "Dimension Description": "Monoloudness",
          "Dimension Category Description": "ALS",
          "RatingDate": "2025-06-07 13:23:51"
        },
        {
          "Level": "4",
          "Comment": "",
          "Other": "",
          "Dimension Description": "Intelligibility",
          "Dimension Category Description": "ALS",
          "RatingDate": "2025-06-07 13:23:51"
        },
        {
          "Level": "4",
          "Comment": "",
          "Other": "",
          "Dimension Description": "Monopitch",
          "Dimension Category Description": "ALS",
          "RatingDate": "2025-06-07 13:23:51"
        },
        {
          "Level": "5",
          "Comment": "",
          "Other": "",
          "Dimension Description": "Distorted vowels",
          "Dimension Category Description": "ALS",
          "RatingDate": "2025-06-07 13:23:51"
        },
        {
          "Level": "5",
          "Comment": "",
          "Other": "",
          "Dimension Description": "Imprecise consonants",
          "Dimension Category Description": "ALS",
          "RatingDate": "2025-06-07 13:23:51"
        },
        {
          "Level": "6",
          "Comment": "",
          "Other": "",
          "Dimension Description": "Naturalness",
          "Dimension Category Description": "ALS",
          "RatingDate": "2025-06-07 13:23:51"
        }
      ]
    },
    {
      "Filename": "db5fac30-88e5-4585-1169-08dc623ec532_1128_5723_16kHz.wav",
      "Created": "2024-07-01 19:01:10",
      "CreatedOrModified": "2025-04-11 11:43:58",
      "Comment": "",
      "Prompt": {
        "Prompt Text": "Five of them refused, but the sixth agreed to lend forty thousand pounds.",
        "Transcript": "Five of them refused, but the sixth agreed to lend forty thousand pounds.",
        "Category Description": "Novel Sentences",
        "Sub Category Description": "",
        "Translation": "Fünf von ihnen weigerten sich, aber der sechste stimmte zu, vierzigtausend Pfund zu leihen."
      },
      "Ratings": [
        {
          "Level": "1",
          "Comment": "",
          "Other": "",
          "Dimension Description": "Audible inspiration",
          "Dimension Category Description": "ALS",
          "RatingDate": "2025-06-07 13:24:29"
        },
        {
          "Level": "1",
          "Comment": "",
          "Other": "",
          "Dimension Description": "Inappropriate silences",
          "Dimension Category Description": "ALS",
          "RatingDate": "2025-06-07 13:24:29"
        },
        {
          "Level": "1",
          "Comment": "",
          "Other": "",
          "Dimension Description": "Nasal emission ",
          "Dimension Category Description": "ALS",
          "RatingDate": "2025-06-07 13:24:29"
        },
        {
          "Level": "1",
          "Comment": "",
          "Other": "",
          "Dimension Description": "Prolonged intervals",
          "Dimension Category Description": "ALS",
          "RatingDate": "2025-06-07 13:24:29"
        },
        {
          "Level": "1",
          "Comment": "",
          "Other": "",
          "Dimension Description": "Prolonged phonemes",
          "Dimension Category Description": "ALS",
          "RatingDate": "2025-06-07 13:24:29"
        },
        {
          "Level": "1",
          "Comment": "",
          "Other": "",
          "Dimension Description": "Short phrases",
          "Dimension Category Description": "ALS",
          "RatingDate": "2025-06-07 13:24:29"
        },
        {
          "Level": "2",
          "Comment": "",
          "Other": "",
          "Dimension Description": "Excess and equal stress",
          "Dimension Category Description": "ALS",
          "RatingDate": "2025-06-07 13:24:29"
        },
        {
          "Level": "2",
          "Comment": "",
          "Other": "",
          "Dimension Description": "Slow rate",
          "Dimension Category Description": "ALS",
          "RatingDate": "2025-06-07 13:24:29"
        },
        {
          "Level": "2",
          "Comment": "",
          "Other": "",
          "Dimension Description": "Strained-strangled voice",
          "Dimension Category Description": "ALS",
          "RatingDate": "2025-06-07 13:24:29"
        },
        {
          "Level": "3",
          "Comment": "",
          "Other": "",
          "Dimension Description": "Breathiness",
          "Dimension Category Description": "ALS",
          "RatingDate": "2025-06-07 13:24:29"
        },
        {
          "Level": "3",
          "Comment": "",
          "Other": "",
          "Dimension Description": "Harsh voice ",
          "Dimension Category Description": "ALS",
          "RatingDate": "2025-06-07 13:24:29"
        },
        {
          "Level": "3",
          "Comment": "",
          "Other": "",
          "Dimension Description": "Low pitch",
          "Dimension Category Description": "ALS",
          "RatingDate": "2025-06-07 13:24:29"
        },
        {
          "Level": "3",
          "Comment": "",
          "Other": "",
          "Dimension Description": "Reduced stress",
          "Dimension Category Description": "ALS",
          "RatingDate": "2025-06-07 13:24:29"
        },
        {
          "Level": "4",
          "Comment": "",
          "Other": "",
          "Dimension Description": "Hypernasality",
          "Dimension Category Description": "ALS",
          "RatingDate": "2025-06-07 13:24:29"
        },
        {
          "Level": "4",
          "Comment": "",
          "Other": "",
          "Dimension Description": "Monoloudness",
          "Dimension Category Description": "ALS",
          "RatingDate": "2025-06-07 13:24:29"
        },
        {
          "Level": "4",
          "Comment": "",
          "Other": "",
          "Dimension Description": "Monopitch",
          "Dimension Category Description": "ALS",
          "RatingDate": "2025-06-07 13:24:29"
        },
        {
          "Level": "5",
          "Comment": "",
          "Other": "",
          "Dimension Description": "Distorted vowels",
          "Dimension Category Description": "ALS",
          "RatingDate": "2025-06-07 13:24:29"
        },
        {
          "Level": "5",
          "Comment": "",
          "Other": "",
          "Dimension Description": "Imprecise consonants",
          "Dimension Category Description": "ALS",
          "RatingDate": "2025-06-07 13:24:29"
        },
        {
          "Level": "5",
          "Comment": "",
          "Other": "",
          "Dimension Description": "Intelligibility",
          "Dimension Category Description": "ALS",
          "RatingDate": "2025-06-07 13:24:29"
        },
        {
          "Level": "6",
          "Comment": "",
          "Other": "",
          "Dimension Description": "Naturalness",
          "Dimension Category Description": "ALS",
          "RatingDate": "2025-06-07 13:24:29"
        }
      ]
    },
    {
      "Filename": "db5fac30-88e5-4585-1169-08dc623ec532_1127_5723_16kHz.wav",
      "Created": "2024-07-01 19:01:30",
      "CreatedOrModified": "2025-04-11 11:44:12",
      "Comment": "",
      "Prompt": {
        "Prompt Text": "He cleared his throat, turned to his companion, and opened his lips.",
        "Transcript": "He cleared his throat, turned to his companion, and opened his lips.",
        "Category Description": "Novel Sentences",
        "Sub Category Description": "",
        "Translation": "Er räucherte sich, wandte sich zu seinem Gefährten und öffnete seine Lippen."
      },
      "Ratings": [
        {
          "Level": "1",
          "Comment": "",
          "Other": "",
          "Dimension Description": "Audible inspiration",
          "Dimension Category Description": "ALS",
          "RatingDate": "2025-06-07 13:25:14"
        },
        {
          "Level": "1",
          "Comment": "",
          "Other": "",
          "Dimension Description": "Inappropriate silences",
          "Dimension Category Description": "ALS",
          "RatingDate": "2025-06-07 13:25:14"
        },
        {
          "Level": "1",
          "Comment": "",
          "Other": "",
          "Dimension Description": "Nasal emission ",
          "Dimension Category Description": "ALS",
          "RatingDate": "2025-06-07 13:25:14"
        },
        {
          "Level": "1",
          "Comment": "",
          "Other": "",
          "Dimension Description": "Prolonged intervals",
          "Dimension Category Description": "ALS",
          "RatingDate": "2025-06-07 13:25:14"
        },
        {
          "Level": "1",
          "Comment": "",
          "Other": "",
          "Dimension Description": "Prolonged phonemes",
          "Dimension Category Description": "ALS",
          "RatingDate": "2025-06-07 13:25:14"
        },
        {
          "Level": "2",
          "Comment": "",
          "Other": "",
          "Dimension Description": "Excess and equal stress",
          "Dimension Category Description": "ALS",
          "RatingDate": "2025-06-07 13:25:14"
        },
        {
          "Level": "2",
          "Comment": "",
          "Other": "",
          "Dimension Description": "Reduced stress",
          "Dimension Category Description": "ALS",
          "RatingDate": "2025-06-07 13:25:14"
        },
        {
          "Level": "2",
          "Comment": "",
          "Other": "",
          "Dimension Description": "Short phrases",
          "Dimension Category Description": "ALS",
          "RatingDate": "2025-06-07 13:25:14"
        },
        {
          "Level": "2",
          "Comment": "",
          "Other": "",
          "Dimension Description": "Strained-strangled voice",
          "Dimension Category Description": "ALS",
          "RatingDate": "2025-06-07 13:25:14"
        },
        {
          "Level": "3",
          "Comment": "",
          "Other": "",
          "Dimension Description": "Breathiness",
          "Dimension Category Description": "ALS",
          "RatingDate": "2025-06-07 13:25:14"
        },
        {
          "Level": "3",
          "Comment": "",
          "Other": "",
          "Dimension Description": "Harsh voice ",
          "Dimension Category Description": "ALS",
          "RatingDate": "2025-06-07 13:25:14"
        },
        {
          "Level": "3",
          "Comment": "",
          "Other": "",
          "Dimension Description": "Low pitch",
          "Dimension Category Description": "ALS",
          "RatingDate": "2025-06-07 13:25:14"
        },
        {
          "Level": "3",
          "Comment": "",
          "Other": "",
          "Dimension Description": "Slow rate",
          "Dimension Category Description": "ALS",
          "RatingDate": "2025-06-07 13:25:14"
        },
        {
          "Level": "4",
          "Comment": "",
          "Other": "",
          "Dimension Description": "Hypernasality",
          "Dimension Category Description": "ALS",
          "RatingDate": "2025-06-07 13:25:14"
        },
        {
          "Level": "4",
          "Comment": "",
          "Other": "",
          "Dimension Description": "Monoloudness",
          "Dimension Category Description": "ALS",
          "RatingDate": "2025-06-07 13:25:14"
        },
        {
          "Level": "4",
          "Comment": "",
          "Other": "",
          "Dimension Description": "Monopitch",
          "Dimension Category Description": "ALS",
          "RatingDate": "2025-06-07 13:25:14"
        },
        {
          "Level": "5",
          "Comment": "",
          "Other": "",
          "Dimension Description": "Distorted vowels",
          "Dimension Category Description": "ALS",
          "RatingDate": "2025-06-07 13:25:14"
        },
        {
          "Level": "5",
          "Comment": "",
          "Other": "",
          "Dimension Description": "Imprecise consonants",
          "Dimension Category Description": "ALS",
          "RatingDate": "2025-06-07 13:25:14"
        },
        {
          "Level": "5",
          "Comment": "",
          "Other": "",
          "Dimension Description": "Intelligibility",
          "Dimension Category Description": "ALS",
          "RatingDate": "2025-06-07 13:25:14"
        },
        {
          "Level": "6",
          "Comment": "",
          "Other": "",
          "Dimension Description": "Naturalness",
          "Dimension Category Description": "ALS",
          "RatingDate": "2025-06-07 13:25:14"
        }
      ]
    },
    {
      "Filename": "db5fac30-88e5-4585-1169-08dc623ec532_1130_5723_16kHz.wav",
      "Created": "2024-07-01 19:02:28",
      "CreatedOrModified": "2025-04-11 11:44:41",
      "Comment": "",
      "Prompt": {
        "Prompt Text": "I'm quite sure you are too kind-hearted to enjoy giving pain to any living creature.",
        "Transcript": "I'm quite sure you are too kind-hearted to enjoy giving pain to any living creature.",
        "Category Description": "Novel Sentences",
        "Sub Category Description": "",
        "Translation": "Ich bin mir sicher, dass du zu gutherzig bist, um jedem Lebewesen Schmerzen zu bereiten."
      },
      "Ratings": []
    },
    {
      "Filename": "db5fac30-88e5-4585-1169-08dc623ec532_1133_5723_16kHz.wav",
      "Created": "2024-07-01 19:03:05",
      "CreatedOrModified": "2025-04-11 11:04:22",
      "Comment": "",
      "Prompt": {
        "Prompt Text": "A vague fear crept over her that he might finally succeed in proving to her that it was her duty to resign.",
        "Transcript": "A vague fear crept over her that he might finally succeed in proving to her that it was her duty to resign.",
        "Category Description": "Novel Sentences",
        "Sub Category Description": "",
        "Translation": "Eine vage Angst schlich über sie, dass es ihm schließlich gelingen könnte, ihr zu beweisen, dass es ihre Pflicht war, zurückzutreten."
      },
      "Ratings": []
    },
    {
      "Filename": "db5fac30-88e5-4585-1169-08dc623ec532_2225_5723_16kHz.wav",
      "Created": "2024-07-01 19:03:29",
      "CreatedOrModified": "2025-04-14 21:53:02",
      "Comment": "",
      "Prompt": {
        "Prompt Text": "\"Oh, I'm not going to call you Stubby Toes any more!\" laughed Sister.",
        "Transcript": "\"Oh, I'm not going to call you Stubby Toes any more!\" laughed Sister.",
        "Category Description": "Novel Sentences",
        "Sub Category Description": "",
        "Translation": "\"Oh, ich werde dich nicht mehr Stubby Toes nennen!\" lachte Schwester."
      },
      "Ratings": []
    },
    {
      "Filename": "db5fac30-88e5-4585-1169-08dc623ec532_1827_5723_16kHz.wav",
      "Created": "2024-07-01 19:04:18",
      "CreatedOrModified": "2025-04-11 11:03:22",
      "Comment": "",
      "Prompt": {
        "Prompt Text": "They tolerated his attendance with an air of aversion as though he were an intruder.",
        "Transcript": "They tolerated his attendance with an air of aversion as though he were an intruder.",
        "Category Description": "Novel Sentences",
        "Sub Category Description": "",
        "Translation": "Sie tolerierten seine Anwesenheit mit einer Abneigung, als ob er ein Eindringling wäre."
      },
      "Ratings": []
    },
    {
      "Filename": "db5fac30-88e5-4585-1169-08dc623ec532_1080_5723_16kHz.wav",
      "Created": "2024-07-01 19:05:31",
      "CreatedOrModified": "2025-04-11 11:02:59",
      "Comment": "",
      "Prompt": {
        "Prompt Text": "How do you keep up to date with the news?",
        "Transcript": "How do you keep up?",
        "Category Description": "Spontaneous Speech Prompts",
        "Sub Category Description": "Open-ended question",
        "Translation": "Wie geht es dir?"
      },
      "Ratings": [
        {
          "Level": "1",
          "Comment": "",
          "Other": "",
          "Dimension Description": "Audible inspiration",
          "Dimension Category Description": "ALS",
          "RatingDate": "2025-06-07 13:26:43"
        },
        {
          "Level": "1",
          "Comment": "",
          "Other": "",
          "Dimension Description": "Excess and equal stress",
          "Dimension Category Description": "ALS",
          "RatingDate": "2025-06-07 13:26:43"
        },
        {
          "Level": "1",
          "Comment": "",
          "Other": "",
          "Dimension Description": "Inappropriate silences",
          "Dimension Category Description": "ALS",
          "RatingDate": "2025-06-07 13:26:43"
        },
        {
          "Level": "1",
          "Comment": "",
          "Other": "",
          "Dimension Description": "Nasal emission ",
          "Dimension Category Description": "ALS",
          "RatingDate": "2025-06-07 13:26:43"
        },
        {
          "Level": "1",
          "Comment": "",
          "Other": "",
          "Dimension Description": "Prolonged intervals",
          "Dimension Category Description": "ALS",
          "RatingDate": "2025-06-07 13:26:43"
        },
        {
          "Level": "1",
          "Comment": "",
          "Other": "",
          "Dimension Description": "Prolonged phonemes",
          "Dimension Category Description": "ALS",
          "RatingDate": "2025-06-07 13:26:43"
        },
        {
          "Level": "1",
          "Comment": "",
          "Other": "",
          "Dimension Description": "Strained-strangled voice",
          "Dimension Category Description": "ALS",
          "RatingDate": "2025-06-07 13:26:43"
        },
        {
          "Level": "2",
          "Comment": "",
          "Other": "",
          "Dimension Description": "Breathiness",
          "Dimension Category Description": "ALS",
          "RatingDate": "2025-06-07 13:26:43"
        },
        {
          "Level": "3",
          "Comment": "",
          "Other": "",
          "Dimension Description": "Harsh voice ",
          "Dimension Category Description": "ALS",
          "RatingDate": "2025-06-07 13:26:43"
        },
        {
          "Level": "3",
          "Comment": "",
          "Other": "",
          "Dimension Description": "Hypernasality",
          "Dimension Category Description": "ALS",
          "RatingDate": "2025-06-07 13:26:43"
        },
        {
          "Level": "3",
          "Comment": "",
          "Other": "",
          "Dimension Description": "Low pitch",
          "Dimension Category Description": "ALS",
          "RatingDate": "2025-06-07 13:26:43"
        },
        {
          "Level": "3",
          "Comment": "",
          "Other": "",
          "Dimension Description": "Reduced stress",
          "Dimension Category Description": "ALS",
          "RatingDate": "2025-06-07 13:26:43"
        },
        {
          "Level": "3",
          "Comment": "",
          "Other": "",
          "Dimension Description": "Short phrases",
          "Dimension Category Description": "ALS",
          "RatingDate": "2025-06-07 13:26:43"
        },
        {
          "Level": "3",
          "Comment": "",
          "Other": "",
          "Dimension Description": "Slow rate",
          "Dimension Category Description": "ALS",
          "RatingDate": "2025-06-07 13:26:43"
        },
        {
          "Level": "4",
          "Comment": "",
          "Other": "",
          "Dimension Description": "Intelligibility",
          "Dimension Category Description": "ALS",
          "RatingDate": "2025-06-07 13:26:43"
        },
        {
          "Level": "4",
          "Comment": "",
          "Other": "",
          "Dimension Description": "Monoloudness",
          "Dimension Category Description": "ALS",
          "RatingDate": "2025-06-07 13:26:43"
        },
        {
          "Level": "4",
          "Comment": "",
          "Other": "",
          "Dimension Description": "Monopitch",
          "Dimension Category Description": "ALS",
          "RatingDate": "2025-06-07 13:26:43"
        },
        {
          "Level": "5",
          "Comment": "",
          "Other": "",
          "Dimension Description": "Distorted vowels",
          "Dimension Category Description": "ALS",
          "RatingDate": "2025-06-07 13:26:43"
        },
        {
          "Level": "5",
          "Comment": "",
          "Other": "",
          "Dimension Description": "Imprecise consonants",
          "Dimension Category Description": "ALS",
          "RatingDate": "2025-06-07 13:26:43"
        },
        {
          "Level": "6",
          "Comment": "",
          "Other": "",
          "Dimension Description": "Naturalness",
          "Dimension Category Description": "ALS",
          "RatingDate": "2025-06-07 13:26:43"
        }
      ]
    },
    {
      "Filename": "db5fac30-88e5-4585-1169-08dc623ec532_90_6782_16kHz.wav",
      "Created": "2024-08-14 19:10:59",
      "CreatedOrModified": "2025-04-11 11:01:38",
      "Comment": "",
      "Prompt": {
        "Prompt Text": "Dislike this song.",
        "Transcript": "Dislike this song.",
        "Category Description": "Digital Assistant Commands",
        "Sub Category Description": "Playing and Controlling Media",
        "Translation": "- Das Lied ist nicht zu hören."
      },
      "Ratings": []
    },
    {
      "Filename": "db5fac30-88e5-4585-1169-08dc623ec532_82_6782_16kHz.wav",
      "Created": "2024-08-14 19:11:21",
      "CreatedOrModified": "2025-04-11 11:01:26",
      "Comment": "",
      "Prompt": {
        "Prompt Text": "When did this song come out?",
        "Transcript": "When did this song come out?",
        "Category Description": "Digital Assistant Commands",
        "Sub Category Description": "Playing and Controlling Media",
        "Translation": "Wann ist das Lied erschienen?"
      },
      "Ratings": []
    },
    {
      "Filename": "db5fac30-88e5-4585-1169-08dc623ec532_1064_5723_16kHz.wav",
      "Created": "2024-07-01 18:52:54",
      "CreatedOrModified": "2025-04-11 11:09:25",
      "Comment": "",
      "Prompt": {
        "Prompt Text": "What's the time?",
        "Transcript": "What's the time?",
        "Category Description": "Digital Assistant Commands",
        "Sub Category Description": "Playing and Controlling Media",
        "Translation": "Wie spät ist es?"
      },
      "Ratings": [
        {
          "Level": "1",
          "Comment": "",
          "Other": "",
          "Dimension Description": "Audible inspiration",
          "Dimension Category Description": "ALS",
          "RatingDate": "2025-06-07 13:21:38"
        },
        {
          "Level": "1",
          "Comment": "",
          "Other": "",
          "Dimension Description": "Excess and equal stress",
          "Dimension Category Description": "ALS",
          "RatingDate": "2025-06-07 13:21:38"
        },
        {
          "Level": "1",
          "Comment": "",
          "Other": "",
          "Dimension Description": "Inappropriate silences",
          "Dimension Category Description": "ALS",
          "RatingDate": "2025-06-07 13:21:38"
        },
        {
          "Level": "1",
          "Comment": "",
          "Other": "",
          "Dimension Description": "Prolonged intervals",
          "Dimension Category Description": "ALS",
          "RatingDate": "2025-06-07 13:21:38"
        },
        {
          "Level": "1",
          "Comment": "",
          "Other": "",
          "Dimension Description": "Prolonged phonemes",
          "Dimension Category Description": "ALS",
          "RatingDate": "2025-06-07 13:21:38"
        },
        {
          "Level": "1",
          "Comment": "",
          "Other": "",
          "Dimension Description": "Short phrases",
          "Dimension Category Description": "ALS",
          "RatingDate": "2025-06-07 13:21:38"
        },
        {
          "Level": "1",
          "Comment": "",
          "Other": "",
          "Dimension Description": "Strained-strangled voice",
          "Dimension Category Description": "ALS",
          "RatingDate": "2025-06-07 13:21:38"
        },
        {
          "Level": "2",
          "Comment": "",
          "Other": "",
          "Dimension Description": "Harsh voice ",
          "Dimension Category Description": "ALS",
          "RatingDate": "2025-06-07 13:21:38"
        },
        {
          "Level": "2",
          "Comment": "",
          "Other": "",
          "Dimension Description": "Nasal emission ",
          "Dimension Category Description": "ALS",
          "RatingDate": "2025-06-07 13:21:38"
        },
        {
          "Level": "2",
          "Comment": "",
          "Other": "",
          "Dimension Description": "Reduced stress",
          "Dimension Category Description": "ALS",
          "RatingDate": "2025-06-07 13:21:38"
        },
        {
          "Level": "3",
          "Comment": "",
          "Other": "",
          "Dimension Description": "Breathiness",
          "Dimension Category Description": "ALS",
          "RatingDate": "2025-06-07 13:21:38"
        },
        {
          "Level": "3",
          "Comment": "",
          "Other": "",
          "Dimension Description": "Hypernasality",
          "Dimension Category Description": "ALS",
          "RatingDate": "2025-06-07 13:21:38"
        },
        {
          "Level": "3",
          "Comment": "",
          "Other": "",
          "Dimension Description": "Intelligibility",
          "Dimension Category Description": "ALS",
          "RatingDate": "2025-06-07 13:21:38"
        },
        {
          "Level": "3",
          "Comment": "",
          "Other": "",
          "Dimension Description": "Low pitch",
          "Dimension Category Description": "ALS",
          "RatingDate": "2025-06-07 13:21:38"
        },
        {
          "Level": "3",
          "Comment": "",
          "Other": "",
          "Dimension Description": "Slow rate",
          "Dimension Category Description": "ALS",
          "RatingDate": "2025-06-07 13:21:38"
        },
        {
          "Level": "4",
          "Comment": "",
          "Other": "",
          "Dimension Description": "Monoloudness",
          "Dimension Category Description": "ALS",
          "RatingDate": "2025-06-07 13:21:38"
        },
        {
          "Level": "4",
          "Comment": "",
          "Other": "",
          "Dimension Description": "Monopitch",
          "Dimension Category Description": "ALS",
          "RatingDate": "2025-06-07 13:21:38"
        },
        {
          "Level": "5",
          "Comment": "",
          "Other": "",
          "Dimension Description": "Distorted vowels",
          "Dimension Category Description": "ALS",
          "RatingDate": "2025-06-07 13:21:38"
        },
        {
          "Level": "5",
          "Comment": "",
          "Other": "",
          "Dimension Description": "Imprecise consonants",
          "Dimension Category Description": "ALS",
          "RatingDate": "2025-06-07 13:21:38"
        },
        {
          "Level": "6",
          "Comment": "",
          "Other": "",
          "Dimension Description": "Naturalness",
          "Dimension Category Description": "ALS",
          "RatingDate": "2025-06-07 13:21:38"
        }
      ]
    },
    {
      "Filename": "db5fac30-88e5-4585-1169-08dc623ec532_1061_5723_16kHz.wav",
      "Created": "2024-07-01 18:53:26",
      "CreatedOrModified": "2025-04-11 11:09:16",
      "Comment": "",
      "Prompt": {
        "Prompt Text": "What restaurants are nearby?",
        "Transcript": "What restaurants are nearby?",
        "Category Description": "Digital Assistant Commands",
        "Sub Category Description": "Playing and Controlling Media",
        "Translation": "Welche Restaurants befinden sich in der Nähe?"
      },
      "Ratings": []
    },
    {
      "Filename": "db5fac30-88e5-4585-1169-08dc623ec532_1058_5723_16kHz.wav",
      "Created": "2024-07-01 18:53:42",
      "CreatedOrModified": "2025-04-11 11:08:50",
      "Comment": "",
      "Prompt": {
        "Prompt Text": "Add this music to favorites.",
        "Transcript": "Add this music to favorites.",
        "Category Description": "Digital Assistant Commands",
        "Sub Category Description": "Playing and Controlling Media",
        "Translation": "Fügen Sie diese Musik zu Favoriten hinzu."
      },
      "Ratings": []
    },
    {
      "Filename": "db5fac30-88e5-4585-1169-08dc623ec532_1054_5723_16kHz.wav",
      "Created": "2024-07-01 18:53:52",
      "CreatedOrModified": "2025-02-23 12:09:29",
      "Comment": "",
      "Prompt": {
        "Prompt Text": "Hang up.",
        "Transcript": "Hang up.",
        "Category Description": "Digital Assistant Commands",
        "Sub Category Description": "Playing and Controlling Media",
        "Translation": "Leg auf."
      },
      "Ratings": []
    },
    {
      "Filename": "db5fac30-88e5-4585-1169-08dc623ec532_1071_5723_16kHz.wav",
      "Created": "2024-07-01 18:54:05",
      "CreatedOrModified": "2025-02-23 12:08:30",
      "Comment": "",
      "Prompt": {
        "Prompt Text": "Turn off heat.",
        "Transcript": "Turn off heat.",
        "Category Description": "Digital Assistant Commands",
        "Sub Category Description": "Playing and Controlling Media",
        "Translation": "Hitze abschalten."
      },
      "Ratings": []
    },
    {
      "Filename": "db5fac30-88e5-4585-1169-08dc623ec532_1066_5723_16kHz.wav",
      "Created": "2024-07-01 18:54:25",
      "CreatedOrModified": "2025-02-23 12:08:42",
      "Comment": "",
      "Prompt": {
        "Prompt Text": "What's the weather like today?",
        "Transcript": "What's the weather like today? ",
        "Category Description": "Digital Assistant Commands",
        "Sub Category Description": "Playing and Controlling Media",
        "Translation": "Wie ist das Wetter heute?"
      },
      "Ratings": []
    },
    {
      "Filename": "db5fac30-88e5-4585-1169-08dc623ec532_1075_5723_16kHz.wav",
      "Created": "2024-07-01 18:54:38",
      "CreatedOrModified": "2025-02-23 12:08:51",
      "Comment": "",
      "Prompt": {
        "Prompt Text": "Turn on all switches.",
        "Transcript": "Turn on all switches.",
        "Category Description": "Digital Assistant Commands",
        "Sub Category Description": "Playing and Controlling Media",
        "Translation": "Schalten Sie alle Schalter ein."
      },
      "Ratings": []
    },
    {
      "Filename": "db5fac30-88e5-4585-1169-08dc623ec532_1072_5723_16kHz.wav",
      "Created": "2024-07-01 18:54:56",
      "CreatedOrModified": "2025-02-23 12:09:00",
      "Comment": "",
      "Prompt": {
        "Prompt Text": "Increase volume to maximum.",
        "Transcript": "Increase volume to maximum.",
        "Category Description": "Digital Assistant Commands",
        "Sub Category Description": "Playing and Controlling Media",
        "Translation": "Volumen auf Maximum erhöhen."
      },
      "Ratings": []
    },
    {
      "Filename": "db5fac30-88e5-4585-1169-08dc623ec532_1068_5723_16kHz.wav",
      "Created": "2024-07-01 18:55:09",
      "CreatedOrModified": "2025-02-23 12:09:09",
      "Comment": "",
      "Prompt": {
        "Prompt Text": "Lower the temperature.",
        "Transcript": "Lower the temperature.",
        "Category Description": "Digital Assistant Commands",
        "Sub Category Description": "Playing and Controlling Media",
        "Translation": "Senken Sie die Temperatur."
      },
      "Ratings": []
    },
    {
      "Filename": "db5fac30-88e5-4585-1169-08dc623ec532_1056_5723_16kHz.wav",
      "Created": "2024-07-01 18:55:23",
      "CreatedOrModified": "2025-04-15 14:06:17",
      "Comment": "",
      "Prompt": {
        "Prompt Text": "Decrease volume to minimum.",
        "Transcript": "(uh) Decrease volume to minimum.",
        "Category Description": "Digital Assistant Commands",
        "Sub Category Description": "Playing and Controlling Media",
        "Translation": "- Volumen auf ein Minimum reduzieren."
      },
      "Ratings": []
    },
    {
      "Filename": "db5fac30-88e5-4585-1169-08dc623ec532_1055_5723_16kHz.wav",
      "Created": "2024-07-01 18:55:52",
      "CreatedOrModified": "2025-02-23 12:09:38",
      "Comment": "",
      "Prompt": {
        "Prompt Text": "Make the text larger.",
        "Transcript": "Make the text larger.",
        "Category Description": "Digital Assistant Commands",
        "Sub Category Description": "Playing and Controlling Media",
        "Translation": "Machen Sie den Text größer."
      },
      "Ratings": []
    },
    {
      "Filename": "db5fac30-88e5-4585-1169-08dc623ec532_1053_5723_16kHz.wav",
      "Created": "2024-07-01 18:56:30",
      "CreatedOrModified": "2025-02-23 12:10:03",
      "Comment": "",
      "Prompt": {
        "Prompt Text": "What's on my shopping list?",
        "Transcript": "What's on my shopping list?",
        "Category Description": "Digital Assistant Commands",
        "Sub Category Description": "Playing and Controlling Media",
        "Translation": "Was steht auf meiner Einkaufsliste?"
      },
      "Ratings": []
    },
    {
      "Filename": "db5fac30-88e5-4585-1169-08dc623ec532_1070_5723_16kHz.wav",
      "Created": "2024-07-01 18:56:42",
      "CreatedOrModified": "2025-02-23 12:10:12",
      "Comment": "",
      "Prompt": {
        "Prompt Text": "Tell me the news.",
        "Transcript": "Tell me the news.",
        "Category Description": "Digital Assistant Commands",
        "Sub Category Description": "Playing and Controlling Media",
        "Translation": "Erzählen Sie mir die Nachrichten."
      },
      "Ratings": []
    },
    {
      "Filename": "db5fac30-88e5-4585-1169-08dc623ec532_1059_5723_16kHz.wav",
      "Created": "2024-07-01 18:56:56",
      "CreatedOrModified": "2025-04-11 11:08:17",
      "Comment": "",
      "Prompt": {
        "Prompt Text": "Open reminders.",
        "Transcript": "Open reminders.",
        "Category Description": "Digital Assistant Commands",
        "Sub Category Description": "Playing and Controlling Media",
        "Translation": "Erinnerungen öffnen."
      },
      "Ratings": []
    },
    {
      "Filename": "db5fac30-88e5-4585-1169-08dc623ec532_1052_5723_16kHz.wav",
      "Created": "2024-07-01 18:57:08",
      "CreatedOrModified": "2025-04-11 11:08:06",
      "Comment": "",
      "Prompt": {
        "Prompt Text": "Find my phone.",
        "Transcript": "Find my phone.",
        "Category Description": "Digital Assistant Commands",
        "Sub Category Description": "Playing and Controlling Media",
        "Translation": "Such mein Handy."
      },
      "Ratings": []
    },
    {
      "Filename": "db5fac30-88e5-4585-1169-08dc623ec532_1057_5723_16kHz.wav",
      "Created": "2024-07-01 18:57:19",
      "CreatedOrModified": "2025-04-11 11:07:45",
      "Comment": "",
      "Prompt": {
        "Prompt Text": "What's the temperature in the living room?",
        "Transcript": "What's the temperature in the living room?",
        "Category Description": "Digital Assistant Commands",
        "Sub Category Description": "Playing and Controlling Media",
        "Translation": "Wie ist die Temperatur im Wohnzimmer?"
      },
      "Ratings": []
    },
    {
      "Filename": "db5fac30-88e5-4585-1169-08dc623ec532_1062_5723_16kHz.wav",
      "Created": "2024-07-01 18:57:47",
      "CreatedOrModified": "2025-04-11 11:07:55",
      "Comment": "",
      "Prompt": {
        "Prompt Text": "Answer the call.",
        "Transcript": "Answer the call.",
        "Category Description": "Digital Assistant Commands",
        "Sub Category Description": "Playing and Controlling Media",
        "Translation": "Geh ran."
      },
      "Ratings": []
    },
    {
      "Filename": "db5fac30-88e5-4585-1169-08dc623ec532_1060_5723_16kHz.wav",
      "Created": "2024-07-01 18:58:04",
      "CreatedOrModified": "2025-04-11 11:09:04",
      "Comment": "",
      "Prompt": {
        "Prompt Text": "What's on my calendar tomorrow?",
        "Transcript": "What's on my calendar tomorrow?",
        "Category Description": "Digital Assistant Commands",
        "Sub Category Description": "Playing and Controlling Media",
        "Translation": "Was steht morgen in meinem Kalender?"
      },
      "Ratings": []
    },
    {
      "Filename": "db5fac30-88e5-4585-1169-08dc623ec532_1073_5723_16kHz.wav",
      "Created": "2024-07-01 18:58:14",
      "CreatedOrModified": "2025-04-11 11:06:30",
      "Comment": "",
      "Prompt": {
        "Prompt Text": "Start listening",
        "Transcript": "Start listening",
        "Category Description": "Digital Assistant Commands",
        "Sub Category Description": "Playing and Controlling Media",
        "Translation": "Fangen Sie an zu hören"
      },
      "Ratings": []
    },
    {
      "Filename": "db5fac30-88e5-4585-1169-08dc623ec532_1067_5723_16kHz.wav",
      "Created": "2024-07-01 18:58:28",
      "CreatedOrModified": "2025-04-11 11:06:21",
      "Comment": "",
      "Prompt": {
        "Prompt Text": "Stop listening",
        "Transcript": "Stop listening",
        "Category Description": "Digital Assistant Commands",
        "Sub Category Description": "Playing and Controlling Media",
        "Translation": "Hör auf zu hören."
      },
      "Ratings": []
    },
    {
      "Filename": "db5fac30-88e5-4585-1169-08dc623ec532_1076_5723_16kHz.wav",
      "Created": "2024-07-01 18:58:54",
      "CreatedOrModified": "2025-04-15 14:07:07",
      "Comment": "",
      "Prompt": {
        "Prompt Text": "Call area code 053-621-4879.",
        "Transcript": "Call area code 053-621-4879 (owa-).",
        "Category Description": "Digital Assistant Commands",
        "Sub Category Description": "Playing and Controlling Media",
        "Translation": "Rufnummer 053-621-4879 (owa-)."
      },
      "Ratings": []
    },
    {
      "Filename": "db5fac30-88e5-4585-1169-08dc623ec532_1069_5723_16kHz.wav",
      "Created": "2024-07-01 18:59:10",
      "CreatedOrModified": "2025-04-11 11:04:55",
      "Comment": "",
      "Prompt": {
        "Prompt Text": "Stop the call.",
        "Transcript": "Stop the call.",
        "Category Description": "Digital Assistant Commands",
        "Sub Category Description": "Playing and Controlling Media",
        "Translation": "Hör auf zu telefonieren."
      },
      "Ratings": []
    },
    {
      "Filename": "db5fac30-88e5-4585-1169-08dc623ec532_1065_5723_16kHz.wav",
      "Created": "2024-07-01 18:59:24",
      "CreatedOrModified": "2025-04-11 11:04:43",
      "Comment": "",
      "Prompt": {
        "Prompt Text": "Skip this song.",
        "Transcript": "Skip this song.",
        "Category Description": "Digital Assistant Commands",
        "Sub Category Description": "Playing and Controlling Media",
        "Translation": "Überspring das Lied."
      },
      "Ratings": []
    },
    {
      "Filename": "db5fac30-88e5-4585-1169-08dc623ec532_1074_5723_16kHz.wav",
      "Created": "2024-05-19 19:36:28",
      "CreatedOrModified": "2025-04-11 11:10:41",
      "Comment": "",
      "Prompt": {
        "Prompt Text": "Turn on cooling.",
        "Transcript": "(uh huh) Turn on cooling.",
        "Category Description": "Digital Assistant Commands",
        "Sub Category Description": "Playing and Controlling Media",
        "Translation": "- Schalten Sie die Kühlung ein."
      },
      "Ratings": [
        {
          "Level": "1",
          "Comment": "",
          "Other": "",
          "Dimension Description": "Audible inspiration",
          "Dimension Category Description": "ALS",
          "RatingDate": "2025-06-07 13:18:55"
        },
        {
          "Level": "1",
          "Comment": "",
          "Other": "",
          "Dimension Description": "Inappropriate silences",
          "Dimension Category Description": "ALS",
          "RatingDate": "2025-06-07 13:18:55"
        },
        {
          "Level": "1",
          "Comment": "",
          "Other": "",
          "Dimension Description": "Nasal emission ",
          "Dimension Category Description": "ALS",
          "RatingDate": "2025-06-07 13:18:55"
        },
        {
          "Level": "1",
          "Comment": "",
          "Other": "",
          "Dimension Description": "Prolonged intervals",
          "Dimension Category Description": "ALS",
          "RatingDate": "2025-06-07 13:18:55"
        },
        {
          "Level": "1",
          "Comment": "",
          "Other": "",
          "Dimension Description": "Prolonged phonemes",
          "Dimension Category Description": "ALS",
          "RatingDate": "2025-06-07 13:18:55"
        },
        {
          "Level": "1",
          "Comment": "",
          "Other": "",
          "Dimension Description": "Strained-strangled voice",
          "Dimension Category Description": "ALS",
          "RatingDate": "2025-06-07 13:18:55"
        },
        {
          "Level": "2",
          "Comment": "",
          "Other": "",
          "Dimension Description": "Hypernasality",
          "Dimension Category Description": "ALS",
          "RatingDate": "2025-06-07 13:18:55"
        },
        {
          "Level": "2",
          "Comment": "",
          "Other": "",
          "Dimension Description": "Reduced stress",
          "Dimension Category Description": "ALS",
          "RatingDate": "2025-06-07 13:18:55"
        },
        {
          "Level": "2",
          "Comment": "",
          "Other": "",
          "Dimension Description": "Short phrases",
          "Dimension Category Description": "ALS",
          "RatingDate": "2025-06-07 13:18:55"
        },
        {
          "Level": "2",
          "Comment": "",
          "Other": "",
          "Dimension Description": "Slow rate",
          "Dimension Category Description": "ALS",
          "RatingDate": "2025-06-07 13:18:55"
        },
        {
          "Level": "3",
          "Comment": "",
          "Other": "",
          "Dimension Description": "Breathiness",
          "Dimension Category Description": "ALS",
          "RatingDate": "2025-06-07 13:18:55"
        },
        {
          "Level": "3",
          "Comment": "",
          "Other": "",
          "Dimension Description": "Excess and equal stress",
          "Dimension Category Description": "ALS",
          "RatingDate": "2025-06-07 13:18:55"
        },
        {
          "Level": "3",
          "Comment": "",
          "Other": "",
          "Dimension Description": "Harsh voice ",
          "Dimension Category Description": "ALS",
          "RatingDate": "2025-06-07 13:18:55"
        },
        {
          "Level": "3",
          "Comment": "",
          "Other": "",
          "Dimension Description": "Low pitch",
          "Dimension Category Description": "ALS",
          "RatingDate": "2025-06-07 13:18:55"
        },
        {
          "Level": "4",
          "Comment": "",
          "Other": "",
          "Dimension Description": "Intelligibility",
          "Dimension Category Description": "ALS",
          "RatingDate": "2025-06-07 13:18:55"
        },
        {
          "Level": "4",
          "Comment": "",
          "Other": "",
          "Dimension Description": "Monoloudness",
          "Dimension Category Description": "ALS",
          "RatingDate": "2025-06-07 13:18:55"
        },
        {
          "Level": "5",
          "Comment": "",
          "Other": "",
          "Dimension Description": "Distorted vowels",
          "Dimension Category Description": "ALS",
          "RatingDate": "2025-06-07 13:18:55"
        },
        {
          "Level": "5",
          "Comment": "",
          "Other": "",
          "Dimension Description": "Imprecise consonants",
          "Dimension Category Description": "ALS",
          "RatingDate": "2025-06-07 13:18:55"
        },
        {
          "Level": "5",
          "Comment": "",
          "Other": "",
          "Dimension Description": "Monopitch",
          "Dimension Category Description": "ALS",
          "RatingDate": "2025-06-07 13:18:55"
        },
        {
          "Level": "6",
          "Comment": "",
          "Other": "",
          "Dimension Description": "Naturalness",
          "Dimension Category Description": "ALS",
          "RatingDate": "2025-06-07 13:18:55"
        }
      ]
    },
    {
      "Filename": "db5fac30-88e5-4585-1169-08dc623ec532_1063_5723_16kHz.wav",
      "Created": "2024-05-19 19:44:43",
      "CreatedOrModified": "2025-04-11 11:10:08",
      "Comment": "",
      "Prompt": {
        "Prompt Text": "Turn off the TV.",
        "Transcript": "Turn off the TV.",
        "Category Description": "Digital Assistant Commands",
        "Sub Category Description": "Playing and Controlling Media",
        "Translation": "Schalten Sie den Fernseher aus."
      },
      "Ratings": [
        {
          "Level": "1",
          "Comment": "",
          "Other": "",
          "Dimension Description": "Audible inspiration",
          "Dimension Category Description": "ALS",
          "RatingDate": "2025-06-07 13:20:25"
        },
        {
          "Level": "1",
          "Comment": "",
          "Other": "",
          "Dimension Description": "Inappropriate silences",
          "Dimension Category Description": "ALS",
          "RatingDate": "2025-06-07 13:20:25"
        },
        {
          "Level": "1",
          "Comment": "",
          "Other": "",
          "Dimension Description": "Prolonged intervals",
          "Dimension Category Description": "ALS",
          "RatingDate": "2025-06-07 13:20:25"
        },
        {
          "Level": "1",
          "Comment": "",
          "Other": "",
          "Dimension Description": "Prolonged phonemes",
          "Dimension Category Description": "ALS",
          "RatingDate": "2025-06-07 13:20:25"
        },
        {
          "Level": "1",
          "Comment": "",
          "Other": "",
          "Dimension Description": "Short phrases",
          "Dimension Category Description": "ALS",
          "RatingDate": "2025-06-07 13:20:25"
        },
        {
          "Level": "1",
          "Comment": "",
          "Other": "",
          "Dimension Description": "Strained-strangled voice",
          "Dimension Category Description": "ALS",
          "RatingDate": "2025-06-07 13:20:25"
        },
        {
          "Level": "2",
          "Comment": "",
          "Other": "",
          "Dimension Description": "Harsh voice ",
          "Dimension Category Description": "ALS",
          "RatingDate": "2025-06-07 13:20:25"
        },
        {
          "Level": "2",
          "Comment": "",
          "Other": "",
          "Dimension Description": "Nasal emission ",
          "Dimension Category Description": "ALS",
          "RatingDate": "2025-06-07 13:20:25"
        },
        {
          "Level": "2",
          "Comment": "",
          "Other": "",
          "Dimension Description": "Reduced stress",
          "Dimension Category Description": "ALS",
          "RatingDate": "2025-06-07 13:20:25"
        },
        {
          "Level": "2",
          "Comment": "",
          "Other": "",
          "Dimension Description": "Slow rate",
          "Dimension Category Description": "ALS",
          "RatingDate": "2025-06-07 13:20:25"
        },
        {
          "Level": "3",
          "Comment": "",
          "Other": "",
          "Dimension Description": "Breathiness",
          "Dimension Category Description": "ALS",
          "RatingDate": "2025-06-07 13:20:25"
        },
        {
          "Level": "3",
          "Comment": "",
          "Other": "",
          "Dimension Description": "Excess and equal stress",
          "Dimension Category Description": "ALS",
          "RatingDate": "2025-06-07 13:20:25"
        },
        {
          "Level": "3",
          "Comment": "",
          "Other": "",
          "Dimension Description": "Intelligibility",
          "Dimension Category Description": "ALS",
          "RatingDate": "2025-06-07 13:20:25"
        },
        {
          "Level": "3",
          "Comment": "",
          "Other": "",
          "Dimension Description": "Low pitch",
          "Dimension Category Description": "ALS",
          "RatingDate": "2025-06-07 13:20:25"
        },
        {
          "Level": "3",
          "Comment": "",
          "Other": "",
          "Dimension Description": "Monoloudness",
          "Dimension Category Description": "ALS",
          "RatingDate": "2025-06-07 13:20:25"
        },
        {
          "Level": "4",
          "Comment": "",
          "Other": "",
          "Dimension Description": "Hypernasality",
          "Dimension Category Description": "ALS",
          "RatingDate": "2025-06-07 13:20:25"
        },
        {
          "Level": "4",
          "Comment": "",
          "Other": "",
          "Dimension Description": "Monopitch",
          "Dimension Category Description": "ALS",
          "RatingDate": "2025-06-07 13:20:25"
        },
        {
          "Level": "5",
          "Comment": "",
          "Other": "",
          "Dimension Description": "Distorted vowels",
          "Dimension Category Description": "ALS",
          "RatingDate": "2025-06-07 13:20:25"
        },
        {
          "Level": "5",
          "Comment": "",
          "Other": "",
          "Dimension Description": "Imprecise consonants",
          "Dimension Category Description": "ALS",
          "RatingDate": "2025-06-07 13:20:25"
        },
        {
          "Level": "6",
          "Comment": "",
          "Other": "",
          "Dimension Description": "Naturalness",
          "Dimension Category Description": "ALS",
          "RatingDate": "2025-06-07 13:20:25"
        }
      ]
    },
    {
      "Filename": "db5fac30-88e5-4585-1169-08dc623ec532_81_6782_16kHz.wav",
      "Created": "2024-08-14 19:13:21",
      "CreatedOrModified": "2025-04-11 10:53:16",
      "Comment": "",
      "Prompt": {
        "Prompt Text": "Like this song.",
        "Transcript": "Like this song.",
        "Category Description": "Digital Assistant Commands",
        "Sub Category Description": "Playing and Controlling Media",
        "Translation": "Wie dieses Lied."
      },
      "Ratings": []
    },
    {
      "Filename": "db5fac30-88e5-4585-1169-08dc623ec532_21_6782_16kHz.wav",
      "Created": "2024-08-14 19:14:28",
      "CreatedOrModified": "2025-03-08 22:46:07",
      "Comment": "",
      "Prompt": {
        "Prompt Text": "Turn down the volume.",
        "Transcript": "Turn down the volume.",
        "Category Description": "Digital Assistant Commands",
        "Sub Category Description": "Playing and Controlling Media",
        "Translation": "Drehen Sie die Lautstärke."
      },
      "Ratings": []
    },
    {
      "Filename": "db5fac30-88e5-4585-1169-08dc623ec532_73_6782_16kHz.wav",
      "Created": "2024-08-14 19:15:26",
      "CreatedOrModified": "2025-03-08 22:45:03",
      "Comment": "",
      "Prompt": {
        "Prompt Text": "Unlock the front door.",
        "Transcript": "Unlock the front door.",
        "Category Description": "Digital Assistant Commands",
        "Sub Category Description": "Control Your Smart Home",
        "Translation": "Schließ die Vordertür auf."
      },
      "Ratings": []
    },
    {
      "Filename": "db5fac30-88e5-4585-1169-08dc623ec532_51_6782_16kHz.wav",
      "Created": "2024-08-14 19:13:37",
      "CreatedOrModified": "2025-04-11 10:53:27",
      "Comment": "",
      "Prompt": {
        "Prompt Text": "Answer the door.",
        "Transcript": "Answer the door.",
        "Category Description": "Digital Assistant Commands",
        "Sub Category Description": "Control Your Smart Home",
        "Translation": "Geh zur Tür."
      },
      "Ratings": []
    },
    {
      "Filename": "db5fac30-88e5-4585-1169-08dc623ec532_45_6782_16kHz.wav",
      "Created": "2024-08-14 19:14:02",
      "CreatedOrModified": "2025-04-11 11:00:17",
      "Comment": "",
      "Prompt": {
        "Prompt Text": "Make it warmer.",
        "Transcript": "Make it warmer.",
        "Category Description": "Digital Assistant Commands",
        "Sub Category Description": "Control Your Smart Home",
        "Translation": "Mach es wärmer."
      },
      "Ratings": []
    },
    {
      "Filename": "db5fac30-88e5-4585-1169-08dc623ec532_18_6782_16kHz.wav",
      "Created": "2024-08-14 19:13:05",
      "CreatedOrModified": "2025-01-04 00:40:42",
      "Comment": "",
      "Prompt": {
        "Prompt Text": "Turn on heat.",
        "Transcript": "Turn on heat.",
        "Category Description": "Digital Assistant Commands",
        "Sub Category Description": "Control Your Smart Home",
        "Translation": "- Mach die Hitze an."
      },
      "Ratings": []
    },
    {
      "Filename": "db5fac30-88e5-4585-1169-08dc623ec532_50_6782_16kHz.wav",
      "Created": "2024-08-14 19:17:35",
      "CreatedOrModified": "2025-04-11 10:59:18",
      "Comment": "",
      "Prompt": {
        "Prompt Text": "Raise the temperature.",
        "Transcript": "Raise the temperature.",
        "Category Description": "Digital Assistant Commands",
        "Sub Category Description": "Control Your Smart Home",
        "Translation": "Erhöhen Sie die Temperatur."
      },
      "Ratings": []
    },
    {
      "Filename": "db5fac30-88e5-4585-1169-08dc623ec532_69_6782_16kHz.wav",
      "Created": "2024-08-14 19:16:06",
      "CreatedOrModified": "2025-03-08 22:45:42",
      "Comment": "",
      "Prompt": {
        "Prompt Text": "Turn off all switches.",
        "Transcript": "Turn off all switches.",
        "Category Description": "Digital Assistant Commands",
        "Sub Category Description": "Control Your Smart Home",
        "Translation": "Schalten Sie alle Schalter ab."
      },
      "Ratings": []
    },
    {
      "Filename": "db5fac30-88e5-4585-1169-08dc623ec532_84_6782_16kHz.wav",
      "Created": "2024-08-14 19:16:26",
      "CreatedOrModified": "2025-04-11 11:00:07",
      "Comment": "",
      "Prompt": {
        "Prompt Text": "Do I need an umbrella today?",
        "Transcript": "Do I need an umbrella today?",
        "Category Description": "Digital Assistant Commands",
        "Sub Category Description": "Get News, Weather, and Traffic Updates",
        "Translation": "Brauche ich heute einen Schirm?"
      },
      "Ratings": []
    },
    {
      "Filename": "db5fac30-88e5-4585-1169-08dc623ec532_25_6782_16kHz.wav",
      "Created": "2024-08-14 19:12:33",
      "CreatedOrModified": "2025-04-11 11:00:39",
      "Comment": "",
      "Prompt": {
        "Prompt Text": "When does the next train arrive?",
        "Transcript": "When does the next train arrive?",
        "Category Description": "Digital Assistant Commands",
        "Sub Category Description": "Get News, Weather, and Traffic Updates",
        "Translation": "Wann kommt der nächste Zug an?"
      },
      "Ratings": []
    },
    {
      "Filename": "db5fac30-88e5-4585-1169-08dc623ec532_63_6782_16kHz.wav",
      "Created": "2024-08-14 19:14:15",
      "CreatedOrModified": "2025-03-08 22:45:56",
      "Comment": "",
      "Prompt": {
        "Prompt Text": "When is it going to rain?",
        "Transcript": "When is it going to rain?",
        "Category Description": "Digital Assistant Commands",
        "Sub Category Description": "Get News, Weather, and Traffic Updates",
        "Translation": "Wann wird es regnen?"
      },
      "Ratings": []
    },
    {
      "Filename": "db5fac30-88e5-4585-1169-08dc623ec532_34_6782_16kHz.wav",
      "Created": "2024-08-14 19:15:44",
      "CreatedOrModified": "2025-03-08 22:45:23",
      "Comment": "",
      "Prompt": {
        "Prompt Text": "Brighten the screen.",
        "Transcript": "Brighten the screen.",
        "Category Description": "Digital Assistant Commands",
        "Sub Category Description": "Phone Operations",
        "Translation": "- Erhellen Sie den Bildschirm."
      },
      "Ratings": []
    },
    {
      "Filename": "db5fac30-88e5-4585-1169-08dc623ec532_35_6782_16kHz.wav",
      "Created": "2024-08-14 19:12:52",
      "CreatedOrModified": "2025-01-04 00:40:31",
      "Comment": "",
      "Prompt": {
        "Prompt Text": "Read my new email.",
        "Transcript": "Read my new email.",
        "Category Description": "Digital Assistant Commands",
        "Sub Category Description": "Phone Operations",
        "Translation": "Lies meine neue E-Mail."
      },
      "Ratings": []
    },
    {
      "Filename": "db5fac30-88e5-4585-1169-08dc623ec532_47_6782_16kHz.wav",
      "Created": "2024-08-14 19:12:12",
      "CreatedOrModified": "2025-04-11 11:01:04",
      "Comment": "",
      "Prompt": {
        "Prompt Text": "Who won the gold medal in men's figure skating in the 1952 Winter Olympics?",
        "Transcript": "Who won the gold medal in men's figure skating in the 1952 Winter Olympics?",
        "Category Description": "Digital Assistant Commands",
        "Sub Category Description": "Online Search",
        "Translation": "Wer gewann die Goldmedaille bei den Herren-Eislauf-Wahlspielen 1952?"
      },
      "Ratings": []
    },
    {
      "Filename": "db5fac30-88e5-4585-1169-08dc623ec532_67_6782_16kHz.wav",
      "Created": "2024-08-14 19:14:47",
      "CreatedOrModified": "2025-03-08 22:44:43",
      "Comment": "",
      "Prompt": {
        "Prompt Text": "Show me my alarms.",
        "Transcript": "Show me my alarms.",
        "Category Description": "Digital Assistant Commands",
        "Sub Category Description": "Everyday Tasks and Planning",
        "Translation": "Zeig mir meine Alarmanlage."
      },
      "Ratings": []
    },
    {
      "Filename": "db5fac30-88e5-4585-1169-08dc623ec532_19_6782_16kHz.wav",
      "Created": "2024-08-14 19:16:49",
      "CreatedOrModified": "2025-04-14 21:52:14",
      "Comment": "",
      "Prompt": {
        "Prompt Text": "Set a reminder to take Spironolactone at 9 PM.",
        "Transcript": "Set a reminder to take Spironolactone at 9 PM.",
        "Category Description": "Digital Assistant Commands",
        "Sub Category Description": "Everyday Tasks and Planning",
        "Translation": "Stellen Sie eine Erinnerung an Spironolacton um 21 Uhr ein."
      },
      "Ratings": []
    },
    {
      "Filename": "db5fac30-88e5-4585-1169-08dc623ec532_72_6782_16kHz.wav",
      "Created": "2024-08-14 19:18:37",
      "CreatedOrModified": "2025-04-11 10:59:06",
      "Comment": "",
      "Prompt": {
        "Prompt Text": "How many refills are left on my estradiol?",
        "Transcript": "How many refills are left on my estradiol?",
        "Category Description": "Digital Assistant Commands",
        "Sub Category Description": "Everyday Tasks and Planning",
        "Translation": "Wie viele Nachfüllungen sind noch auf meinem Estradiol?"
      },
      "Ratings": []
    },
    {
      "Filename": "db5fac30-88e5-4585-1169-08dc623ec532_52_6782_16kHz.wav",
      "Created": "2024-08-14 19:18:56",
      "CreatedOrModified": "2025-04-11 10:58:49",
      "Comment": "",
      "Prompt": {
        "Prompt Text": "Where is my first event tomorrow?",
        "Transcript": "Where is my first event tomorrow?",
        "Category Description": "Digital Assistant Commands",
        "Sub Category Description": "Everyday Tasks and Planning",
        "Translation": "Wo ist mein erstes Event morgen?"
      },
      "Ratings": []
    },
    {
      "Filename": "db5fac30-88e5-4585-1169-08dc623ec532_56_6782_16kHz.wav",
      "Created": "2024-08-14 19:19:09",
      "CreatedOrModified": "2025-04-11 10:58:29",
      "Comment": "",
      "Prompt": {
        "Prompt Text": "What time is it?",
        "Transcript": "What time is it?",
        "Category Description": "Digital Assistant Commands",
        "Sub Category Description": "Everyday Tasks and Planning",
        "Translation": "Wie spät ist es?"
      },
      "Ratings": []
    },
    {
      "Filename": "db5fac30-88e5-4585-1169-08dc623ec532_46_6782_16kHz.wav",
      "Created": "2024-08-14 19:11:38",
      "CreatedOrModified": "2025-04-11 11:01:15",
      "Comment": "",
      "Prompt": {
        "Prompt Text": "What's on my to-do list?",
        "Transcript": "What's on my to-do list?",
        "Category Description": "Digital Assistant Commands",
        "Sub Category Description": "Everyday Tasks and Planning",
        "Translation": "Was steht auf meiner To-Do-Liste?"
      },
      "Ratings": []
    },
    {
      "Filename": "db5fac30-88e5-4585-1169-08dc623ec532_148_5723_16kHz.wav",
      "Created": "2024-07-01 18:59:35",
      "CreatedOrModified": "2025-04-11 11:04:32",
      "Comment": "",
      "Prompt": {
        "Prompt Text": "Cortana.",
        "Transcript": "Cortana.",
        "Category Description": "Digital Assistant Commands",
        "Sub Category Description": "Wake Phrases",
        "Translation": "Cortana. - Ich weiß."
      },
      "Ratings": []
    },
    {
      "Filename": "db5fac30-88e5-4585-1169-08dc623ec532_78_5723_16kHz.wav",
      "Created": "2024-07-01 18:56:04",
      "CreatedOrModified": "2025-02-23 12:09:46",
      "Comment": "",
      "Prompt": {
        "Prompt Text": "Hey Siri.",
        "Transcript": "Hey Siri.",
        "Category Description": "Digital Assistant Commands",
        "Sub Category Description": "Wake Phrases",
        "Translation": "- Hey Siri. - Ich bin ein guter Freund."
      },
      "Ratings": []
    },
    {
      "Filename": "db5fac30-88e5-4585-1169-08dc623ec532_49_5723_16kHz.wav",
      "Created": "2024-07-01 18:56:15",
      "CreatedOrModified": "2025-02-23 12:09:54",
      "Comment": "",
      "Prompt": {
        "Prompt Text": "Hey Google.",
        "Transcript": "Hey Google.",
        "Category Description": "Digital Assistant Commands",
        "Sub Category Description": "Wake Phrases",
        "Translation": "Hey, Google. - Hey, Google."
      },
      "Ratings": []
    },
    {
      "Filename": "db5fac30-88e5-4585-1169-08dc623ec532_78_6782_16kHz.wav",
      "Created": "2024-08-14 19:14:59",
      "CreatedOrModified": "2025-03-08 22:44:53",
      "Comment": "",
      "Prompt": {
        "Prompt Text": "Hey Siri.",
        "Transcript": "Hey Siri.",
        "Category Description": "Digital Assistant Commands",
        "Sub Category Description": "Wake Phrases",
        "Translation": "- Hey Siri. - Ich bin ein guter Freund."
      },
      "Ratings": []
    },
    {
      "Filename": "db5fac30-88e5-4585-1169-08dc623ec532_39_6782_16kHz.wav",
      "Created": "2024-08-14 19:13:47",
      "CreatedOrModified": "2025-04-11 11:00:26",
      "Comment": "",
      "Prompt": {
        "Prompt Text": "Alexa.",
        "Transcript": "Alexa.",
        "Category Description": "Digital Assistant Commands",
        "Sub Category Description": "Wake Phrases",
        "Translation": "Alexa. - Ich weiß."
      },
      "Ratings": []
    },
    {
      "Filename": "db5fac30-88e5-4585-1169-08dc623ec532_39_5723_16kHz.wav",
      "Created": "2024-05-19 19:45:04",
      "CreatedOrModified": "2025-04-11 11:09:59",
      "Comment": "",
      "Prompt": {
        "Prompt Text": "Alexa.",
        "Transcript": "Alexa.",
        "Category Description": "Digital Assistant Commands",
        "Sub Category Description": "Wake Phrases",
        "Translation": "Alexa. - Ich weiß."
      },
      "Ratings": [
        {
          "Level": "",
          "Comment": "",
          "Other": "",
          "Dimension Description": "Audible inspiration",
          "Dimension Category Description": "ALS",
          "RatingDate": "2025-06-07 13:21:02"
        },
        {
          "Level": "1",
          "Comment": "",
          "Other": "",
          "Dimension Description": "Inappropriate silences",
          "Dimension Category Description": "ALS",
          "RatingDate": "2025-06-07 13:21:02"
        },
        {
          "Level": "1",
          "Comment": "",
          "Other": "",
          "Dimension Description": "Nasal emission ",
          "Dimension Category Description": "ALS",
          "RatingDate": "2025-06-07 13:21:02"
        },
        {
          "Level": "1",
          "Comment": "",
          "Other": "",
          "Dimension Description": "Prolonged intervals",
          "Dimension Category Description": "ALS",
          "RatingDate": "2025-06-07 13:21:02"
        },
        {
          "Level": "1",
          "Comment": "",
          "Other": "",
          "Dimension Description": "Prolonged phonemes",
          "Dimension Category Description": "ALS",
          "RatingDate": "2025-06-07 13:21:02"
        },
        {
          "Level": "1",
          "Comment": "",
          "Other": "",
          "Dimension Description": "Short phrases",
          "Dimension Category Description": "ALS",
          "RatingDate": "2025-06-07 13:21:02"
        },
        {
          "Level": "1",
          "Comment": "",
          "Other": "",
          "Dimension Description": "Strained-strangled voice",
          "Dimension Category Description": "ALS",
          "RatingDate": "2025-06-07 13:21:02"
        },
        {
          "Level": "2",
          "Comment": "",
          "Other": "",
          "Dimension Description": "Intelligibility",
          "Dimension Category Description": "ALS",
          "RatingDate": "2025-06-07 13:21:02"
        },
        {
          "Level": "2",
          "Comment": "",
          "Other": "",
          "Dimension Description": "Reduced stress",
          "Dimension Category Description": "ALS",
          "RatingDate": "2025-06-07 13:21:02"
        },
        {
          "Level": "2",
          "Comment": "",
          "Other": "",
          "Dimension Description": "Slow rate",
          "Dimension Category Description": "ALS",
          "RatingDate": "2025-06-07 13:21:02"
        },
        {
          "Level": "3",
          "Comment": "",
          "Other": "",
          "Dimension Description": "Breathiness",
          "Dimension Category Description": "ALS",
          "RatingDate": "2025-06-07 13:21:02"
        },
        {
          "Level": "3",
          "Comment": "",
          "Other": "",
          "Dimension Description": "Harsh voice ",
          "Dimension Category Description": "ALS",
          "RatingDate": "2025-06-07 13:21:02"
        },
        {
          "Level": "3",
          "Comment": "",
          "Other": "",
          "Dimension Description": "Low pitch",
          "Dimension Category Description": "ALS",
          "RatingDate": "2025-06-07 13:21:02"
        },
        {
          "Level": "4",
          "Comment": "",
          "Other": "",
          "Dimension Description": "Excess and equal stress",
          "Dimension Category Description": "ALS",
          "RatingDate": "2025-06-07 13:21:02"
        },
        {
          "Level": "4",
          "Comment": "",
          "Other": "",
          "Dimension Description": "Hypernasality",
          "Dimension Category Description": "ALS",
          "RatingDate": "2025-06-07 13:21:02"
        },
        {
          "Level": "4",
          "Comment": "",
          "Other": "",
          "Dimension Description": "Monoloudness",
          "Dimension Category Description": "ALS",
          "RatingDate": "2025-06-07 13:21:02"
        },
        {
          "Level": "4",
          "Comment": "",
          "Other": "",
          "Dimension Description": "Monopitch",
          "Dimension Category Description": "ALS",
          "RatingDate": "2025-06-07 13:21:02"
        },
        {
          "Level": "5",
          "Comment": "",
          "Other": "",
          "Dimension Description": "Distorted vowels",
          "Dimension Category Description": "ALS",
          "RatingDate": "2025-06-07 13:21:02"
        },
        {
          "Level": "5",
          "Comment": "",
          "Other": "",
          "Dimension Description": "Imprecise consonants",
          "Dimension Category Description": "ALS",
          "RatingDate": "2025-06-07 13:21:02"
        },
        {
          "Level": "6",
          "Comment": "",
          "Other": "",
          "Dimension Description": "Naturalness",
          "Dimension Category Description": "ALS",
          "RatingDate": "2025-06-07 13:21:02"
        }
      ]
    },
    {
      "Filename": "db5fac30-88e5-4585-1169-08dc623ec532_60_5723_16kHz.wav",
      "Created": "2024-05-19 19:44:20",
      "CreatedOrModified": "2025-04-11 11:10:17",
      "Comment": "",
      "Prompt": {
        "Prompt Text": "Hey Facebook.",
        "Transcript": "Hey Facebook.",
        "Category Description": "Digital Assistant Commands",
        "Sub Category Description": "Wake Phrases",
        "Translation": "Hey Facebook."
      },
      "Ratings": [
        {
          "Level": "1",
          "Comment": "",
          "Other": "",
          "Dimension Description": "Audible inspiration",
          "Dimension Category Description": "ALS",
          "RatingDate": "2025-06-07 13:19:33"
        },
        {
          "Level": "1",
          "Comment": "",
          "Other": "",
          "Dimension Description": "Inappropriate silences",
          "Dimension Category Description": "ALS",
          "RatingDate": "2025-06-07 13:19:33"
        },
        {
          "Level": "1",
          "Comment": "",
          "Other": "",
          "Dimension Description": "Nasal emission ",
          "Dimension Category Description": "ALS",
          "RatingDate": "2025-06-07 13:19:33"
        },
        {
          "Level": "1",
          "Comment": "",
          "Other": "",
          "Dimension Description": "Prolonged intervals",
          "Dimension Category Description": "ALS",
          "RatingDate": "2025-06-07 13:19:33"
        },
        {
          "Level": "1",
          "Comment": "",
          "Other": "",
          "Dimension Description": "Prolonged phonemes",
          "Dimension Category Description": "ALS",
          "RatingDate": "2025-06-07 13:19:33"
        },
        {
          "Level": "1",
          "Comment": "",
          "Other": "",
          "Dimension Description": "Short phrases",
          "Dimension Category Description": "ALS",
          "RatingDate": "2025-06-07 13:19:33"
        },
        {
          "Level": "1",
          "Comment": "",
          "Other": "",
          "Dimension Description": "Strained-strangled voice",
          "Dimension Category Description": "ALS",
          "RatingDate": "2025-06-07 13:19:33"
        },
        {
          "Level": "2",
          "Comment": "",
          "Other": "",
          "Dimension Description": "Excess and equal stress",
          "Dimension Category Description": "ALS",
          "RatingDate": "2025-06-07 13:19:33"
        },
        {
          "Level": "2",
          "Comment": "",
          "Other": "",
          "Dimension Description": "Harsh voice ",
          "Dimension Category Description": "ALS",
          "RatingDate": "2025-06-07 13:19:33"
        },
        {
          "Level": "2",
          "Comment": "",
          "Other": "",
          "Dimension Description": "Low pitch",
          "Dimension Category Description": "ALS",
          "RatingDate": "2025-06-07 13:19:33"
        },
        {
          "Level": "2",
          "Comment": "",
          "Other": "",
          "Dimension Description": "Reduced stress",
          "Dimension Category Description": "ALS",
          "RatingDate": "2025-06-07 13:19:33"
        },
        {
          "Level": "2",
          "Comment": "",
          "Other": "",
          "Dimension Description": "Slow rate",
          "Dimension Category Description": "ALS",
          "RatingDate": "2025-06-07 13:19:33"
        },
        {
          "Level": "3",
          "Comment": "",
          "Other": "",
          "Dimension Description": "Breathiness",
          "Dimension Category Description": "ALS",
          "RatingDate": "2025-06-07 13:19:33"
        },
        {
          "Level": "3",
          "Comment": "",
          "Other": "",
          "Dimension Description": "Hypernasality",
          "Dimension Category Description": "ALS",
          "RatingDate": "2025-06-07 13:19:33"
        },
        {
          "Level": "4",
          "Comment": "",
          "Other": "",
          "Dimension Description": "Intelligibility",
          "Dimension Category Description": "ALS",
          "RatingDate": "2025-06-07 13:19:33"
        },
        {
          "Level": "4",
          "Comment": "",
          "Other": "",
          "Dimension Description": "Monoloudness",
          "Dimension Category Description": "ALS",
          "RatingDate": "2025-06-07 13:19:33"
        },
        {
          "Level": "4",
          "Comment": "",
          "Other": "",
          "Dimension Description": "Monopitch",
          "Dimension Category Description": "ALS",
          "RatingDate": "2025-06-07 13:19:33"
        },
        {
          "Level": "5",
          "Comment": "",
          "Other": "",
          "Dimension Description": "Distorted vowels",
          "Dimension Category Description": "ALS",
          "RatingDate": "2025-06-07 13:19:33"
        },
        {
          "Level": "5",
          "Comment": "",
          "Other": "",
          "Dimension Description": "Imprecise consonants",
          "Dimension Category Description": "ALS",
          "RatingDate": "2025-06-07 13:19:33"
        },
        {
          "Level": "6",
          "Comment": "",
          "Other": "",
          "Dimension Description": "Naturalness",
          "Dimension Category Description": "ALS",
          "RatingDate": "2025-06-07 13:19:33"
        }
      ]
    }
  ]
}